clico/__init__.py
clico/clico.py
clico/models.py
clico/utils.py
tests/__init__.py
tests/test_clico.py
tests/test_models.py
tests/test_utils.py
clico-0.2.dist-info/LICENSE
clico-0.2.dist-info/METADATA
clico-0.2.dist-info/WHEEL
clico-0.2.dist-info/top_level.txt
clico-0.2.dist-info/RECORD
