Metadata-Version: 2.1
Name: clico
Version: 0.2
Summary: The library implements create short links via https://cli.com (Ex. cli.co) service.
Home-page: https://github.com/pixel365/clico
Author: pixel365
Author-email: pixel.365.24@gmail.com
License: Apache Software License
Download-URL: https://github.com/pixel365/clico/archive/master.zip
Keywords: cli.com,cli.co,clico,short link
Platform: UNKNOWN
Classifier: Development Status :: 5 - Production/Stable
Classifier: Intended Audience :: Developers
Classifier: License :: OSI Approved :: Apache Software License
Classifier: Programming Language :: Python :: 3 :: Only
Requires-Python: >=3.7
License-File: LICENSE
Requires-Dist: requests (>=2.22.0)
Requires-Dist: pydantic (>=1.7.3)
Requires-Dist: validators (>=0.18.2)
